invenio_rest/__init__.py
invenio_rest/config.py
invenio_rest/csrf.py
invenio_rest/decorators.py
invenio_rest/errors.py
invenio_rest/ext.py
invenio_rest/serializer.py
invenio_rest/views.py
invenio_rest-2.0.5.dist-info/licenses/AUTHORS.rst
invenio_rest-2.0.5.dist-info/licenses/LICENSE
invenio_rest-2.0.5.dist-info/METADATA
invenio_rest-2.0.5.dist-info/WHEEL
invenio_rest-2.0.5.dist-info/entry_points.txt
invenio_rest-2.0.5.dist-info/top_level.txt
invenio_rest-2.0.5.dist-info/RECORD
