Metadata-Version: 2.4
Name: invenio-rest
Version: 2.0.5
Summary: "REST API module for Invenio."
Home-page: https://github.com/inveniosoftware/invenio-rest
Author: CERN
Author-email: info@inveniosoftware.org
License: MIT
Keywords: invenio rest api module
Platform: any
Classifier: Development Status :: 5 - Production/Stable
Requires-Python: >=3.7
License-File: LICENSE
License-File: AUTHORS.rst
Requires-Dist: Flask-CORS>=2.1.0
Requires-Dist: invenio-base<3.0.0,>=2.0.0
Requires-Dist: invenio-logging<5.0.0,>=4.0.0
Requires-Dist: itsdangerous>=2.2.0
Requires-Dist: marshmallow<4.0.0,>=2.15.2
Requires-Dist: webargs<6.0.0,>=5.5.0
Provides-Extra: tests
Requires-Dist: pytest-black-ng>=0.4.0; extra == "tests"
Requires-Dist: pytest-invenio<4.0.0,>=3.0.0; extra == "tests"
Requires-Dist: xmltodict>=0.11.0; extra == "tests"
Requires-Dist: Sphinx>=4.5.0; extra == "tests"
Provides-Extra: cors
Provides-Extra: docs
Dynamic: license-file
